examples/__init__.py
examples/game.py
examples/template_player_object.py
examples/template_scene.py
examples/template_scene1.py
examples/template_scene2.py
simian/audio/__init__.py
simian/audio/audio_manager.py
simian/audio/audios.py
simian/cli/__init__.py
simian/cli/cmd.py
simian/cli/regex.py
simian/exceptions/__init__.py
simian/exceptions/unimplemented_method.py
simian/gameloop/__init__.py
simian/gameloop/game_loop.py
simian/gameobject/__init__.py
simian/gameobject/game_object.py
simian/input/__init__.py
simian/input/keyboard_manager.py
simian/input/mouse_manager.py
simian/physics/__init__.py
simian/physics/bodies.py
simian/physics/colliders.py
simian/physics/collision.py
simian/physics/space.py
simian/renderable/__init__.py
simian/renderable/sample.py
simian/scene/__init__.py
simian/scene/base_scene.py
simian/scene/scene_manager.py
simian/sprite/__init__.py
simian/sprite/sprite.py
simian/templates/__init__.py
simian/templates/sample.py
simian/text/__init__.py
simian/text/text_object.py
simian/utils/__init__.py
simian/utils/lists.py
simian/utils/observer.py
simian/utils/project.py
simian/utils/singleton.py
simian/utils/exception/__init__.py
simian/utils/exception/sample.py
simian/utils/exception/text_exception.py
simian/utils/exception/unimplemented_method.py
simian/window/__init__.py
simian/window/game_canvas.py
simian_engine-0.0.3.dist-info/LICENSE.txt
simian_engine-0.0.3.dist-info/METADATA
simian_engine-0.0.3.dist-info/RECORD
simian_engine-0.0.3.dist-info/WHEEL
simian_engine-0.0.3.dist-info/entry_points.txt
simian_engine-0.0.3.dist-info/top_level.txt
